{
  "entrypoints": [
    "main"
  ],
  "origins": {
    "237": [
      237
    ],
    "17896441": [
      869,
      401
    ],
    "main": [
      354,
      869,
      792
    ],
    "runtime~main": [
      792,
      869,
      354
    ],
    "04da809a": [
      968
    ],
    "12b99b64": [
      674
    ],
    "1319fdf9": [
      752
    ],
    "1973956f": [
      685
    ],
    "1df93b7f": [
      583
    ],
    "1fbf26a4": [
      782
    ],
    "2ec714f2": [
      289
    ],
    "54f44165": [
      924
    ],
    "588bd741": [
      324
    ],
    "5abf42dd": [
      451
    ],
    "5e95c892": [
      647
    ],
    "851cb215": [
      648
    ],
    "8901f887": [
      854
    ],
    "8fd4bb5c": [
      833
    ],
    "92eeeb13": [
      273
    ],
    "980c244d": [
      697
    ],
    "9a4df4ac": [
      295
    ],
    "a7456010": [
      235
    ],
    "a7bd4aaa": [
      98
    ],
    "a94703ab": [
      869,
      48
    ],
    "aba21aa0": [
      742
    ],
    "b64cf4e6": [
      71
    ],
    "c19fadf1": [
      514
    ],
    "c377a04b": [
      361
    ],
    "c9c9b1c0": [
      13
    ],
    "cd93adc3": [
      563
    ],
    "d155309a": [
      787
    ],
    "d7b8612d": [
      383
    ],
    "d90af130": [
      109
    ],
    "ec1a8828": [
      419
    ],
    "styles": [
      48,
      354,
      401,
      792,
      869
    ]
  },
  "assets": {
    "13": {
      "js": [
        {
          "file": "assets/js/c9c9b1c0.c6e2ab92.js",
          "hash": "627f70fea9f01c71",
          "publicPath": "/STELLA_backend/assets/js/c9c9b1c0.c6e2ab92.js"
        }
      ]
    },
    "48": {
      "js": [
        {
          "file": "assets/js/a94703ab.ea41ee4f.js",
          "hash": "80275c1b7f27db50",
          "publicPath": "/STELLA_backend/assets/js/a94703ab.ea41ee4f.js"
        }
      ]
    },
    "71": {
      "js": [
        {
          "file": "assets/js/b64cf4e6.611c8b44.js",
          "hash": "46043f7edade055f",
          "publicPath": "/STELLA_backend/assets/js/b64cf4e6.611c8b44.js"
        }
      ]
    },
    "98": {
      "js": [
        {
          "file": "assets/js/a7bd4aaa.9f738bf8.js",
          "hash": "2f97fa4b87baeb85",
          "publicPath": "/STELLA_backend/assets/js/a7bd4aaa.9f738bf8.js"
        }
      ]
    },
    "109": {
      "js": [
        {
          "file": "assets/js/d90af130.a07cf750.js",
          "hash": "224979e29917cf9d",
          "publicPath": "/STELLA_backend/assets/js/d90af130.a07cf750.js"
        }
      ]
    },
    "235": {
      "js": [
        {
          "file": "assets/js/a7456010.767a0c07.js",
          "hash": "74fb65f3dc0d906e",
          "publicPath": "/STELLA_backend/assets/js/a7456010.767a0c07.js"
        }
      ]
    },
    "237": {
      "js": [
        {
          "file": "assets/js/237.b5f499a0.js",
          "hash": "cce16bb9dd9028fb",
          "publicPath": "/STELLA_backend/assets/js/237.b5f499a0.js"
        }
      ]
    },
    "273": {
      "js": [
        {
          "file": "assets/js/92eeeb13.b9eba6fa.js",
          "hash": "47317a58c6f2a771",
          "publicPath": "/STELLA_backend/assets/js/92eeeb13.b9eba6fa.js"
        }
      ]
    },
    "289": {
      "js": [
        {
          "file": "assets/js/2ec714f2.87e88986.js",
          "hash": "746240502dfb078e",
          "publicPath": "/STELLA_backend/assets/js/2ec714f2.87e88986.js"
        }
      ]
    },
    "295": {
      "js": [
        {
          "file": "assets/js/9a4df4ac.281849ab.js",
          "hash": "010ff45c1f95843a",
          "publicPath": "/STELLA_backend/assets/js/9a4df4ac.281849ab.js"
        }
      ]
    },
    "324": {
      "js": [
        {
          "file": "assets/js/588bd741.4b04703b.js",
          "hash": "a7d57fdc0403dea7",
          "publicPath": "/STELLA_backend/assets/js/588bd741.4b04703b.js"
        }
      ]
    },
    "354": {
      "js": [
        {
          "file": "assets/js/runtime~main.ac6bd8c6.js",
          "hash": "2092d4f05b814afa",
          "publicPath": "/STELLA_backend/assets/js/runtime~main.ac6bd8c6.js"
        }
      ]
    },
    "361": {
      "js": [
        {
          "file": "assets/js/c377a04b.841d49f1.js",
          "hash": "ef2c0f7f445ddd61",
          "publicPath": "/STELLA_backend/assets/js/c377a04b.841d49f1.js"
        }
      ]
    },
    "383": {
      "js": [
        {
          "file": "assets/js/d7b8612d.98f44b58.js",
          "hash": "14783cdf868e87d7",
          "publicPath": "/STELLA_backend/assets/js/d7b8612d.98f44b58.js"
        }
      ]
    },
    "401": {
      "js": [
        {
          "file": "assets/js/17896441.8224eeb0.js",
          "hash": "626223a5062e9ce3",
          "publicPath": "/STELLA_backend/assets/js/17896441.8224eeb0.js"
        }
      ]
    },
    "419": {
      "js": [
        {
          "file": "assets/js/ec1a8828.2d7a8a40.js",
          "hash": "90b36f68e43b659b",
          "publicPath": "/STELLA_backend/assets/js/ec1a8828.2d7a8a40.js"
        }
      ]
    },
    "451": {
      "js": [
        {
          "file": "assets/js/5abf42dd.41bb0375.js",
          "hash": "ca9499ee26033c2e",
          "publicPath": "/STELLA_backend/assets/js/5abf42dd.41bb0375.js"
        }
      ]
    },
    "514": {
      "js": [
        {
          "file": "assets/js/c19fadf1.aa695973.js",
          "hash": "39fd6e0fb032ead2",
          "publicPath": "/STELLA_backend/assets/js/c19fadf1.aa695973.js"
        }
      ]
    },
    "563": {
      "js": [
        {
          "file": "assets/js/cd93adc3.87dda72c.js",
          "hash": "3208cbb6a7775382",
          "publicPath": "/STELLA_backend/assets/js/cd93adc3.87dda72c.js"
        }
      ]
    },
    "583": {
      "js": [
        {
          "file": "assets/js/1df93b7f.dc9eadab.js",
          "hash": "31556a5de07c9e96",
          "publicPath": "/STELLA_backend/assets/js/1df93b7f.dc9eadab.js"
        }
      ]
    },
    "647": {
      "js": [
        {
          "file": "assets/js/5e95c892.56714518.js",
          "hash": "071be72c7bada5ed",
          "publicPath": "/STELLA_backend/assets/js/5e95c892.56714518.js"
        }
      ]
    },
    "648": {
      "js": [
        {
          "file": "assets/js/851cb215.f8f00a77.js",
          "hash": "4362679478126ebc",
          "publicPath": "/STELLA_backend/assets/js/851cb215.f8f00a77.js"
        }
      ]
    },
    "674": {
      "js": [
        {
          "file": "assets/js/12b99b64.1d996860.js",
          "hash": "62ed1451fe72227f",
          "publicPath": "/STELLA_backend/assets/js/12b99b64.1d996860.js"
        }
      ]
    },
    "685": {
      "js": [
        {
          "file": "assets/js/1973956f.671d8c26.js",
          "hash": "6aef8800c91b436b",
          "publicPath": "/STELLA_backend/assets/js/1973956f.671d8c26.js"
        }
      ]
    },
    "697": {
      "js": [
        {
          "file": "assets/js/980c244d.7d3f7d18.js",
          "hash": "066e05aa2f5f3e81",
          "publicPath": "/STELLA_backend/assets/js/980c244d.7d3f7d18.js"
        }
      ]
    },
    "742": {
      "js": [
        {
          "file": "assets/js/aba21aa0.19c07db6.js",
          "hash": "9b0e9d3f7225f0b9",
          "publicPath": "/STELLA_backend/assets/js/aba21aa0.19c07db6.js"
        }
      ]
    },
    "752": {
      "js": [
        {
          "file": "assets/js/1319fdf9.adf6183e.js",
          "hash": "f0a01eba95bd160c",
          "publicPath": "/STELLA_backend/assets/js/1319fdf9.adf6183e.js"
        }
      ]
    },
    "782": {
      "js": [
        {
          "file": "assets/js/1fbf26a4.1130f48d.js",
          "hash": "add2c2c75b455259",
          "publicPath": "/STELLA_backend/assets/js/1fbf26a4.1130f48d.js"
        }
      ]
    },
    "787": {
      "js": [
        {
          "file": "assets/js/d155309a.6eaae6d3.js",
          "hash": "b60f844b52540335",
          "publicPath": "/STELLA_backend/assets/js/d155309a.6eaae6d3.js"
        }
      ]
    },
    "792": {
      "js": [
        {
          "file": "assets/js/main.a7979be1.js",
          "hash": "ed2c19bb5ff02d70",
          "publicPath": "/STELLA_backend/assets/js/main.a7979be1.js"
        }
      ]
    },
    "833": {
      "js": [
        {
          "file": "assets/js/8fd4bb5c.c697a25c.js",
          "hash": "e81c1605e9519a85",
          "publicPath": "/STELLA_backend/assets/js/8fd4bb5c.c697a25c.js"
        }
      ]
    },
    "854": {
      "js": [
        {
          "file": "assets/js/8901f887.3135a904.js",
          "hash": "9e45b7cbbc0b0702",
          "publicPath": "/STELLA_backend/assets/js/8901f887.3135a904.js"
        }
      ]
    },
    "869": {
      "css": [
        {
          "file": "assets/css/styles.8a416dc4.css",
          "hash": "f3236e4cd0d4e5e0",
          "publicPath": "/STELLA_backend/assets/css/styles.8a416dc4.css"
        }
      ]
    },
    "924": {
      "js": [
        {
          "file": "assets/js/54f44165.0f8da5b8.js",
          "hash": "5b93e0f64aec1ad4",
          "publicPath": "/STELLA_backend/assets/js/54f44165.0f8da5b8.js"
        }
      ]
    },
    "968": {
      "js": [
        {
          "file": "assets/js/04da809a.ac550489.js",
          "hash": "8325128125479a0b",
          "publicPath": "/STELLA_backend/assets/js/04da809a.ac550489.js"
        }
      ]
    }
  }
}